LICENSE
MANIFEST.in
README.md
pyproject.toml
setup.cfg
setup.py
docassemble.LAWVCommon.egg-info/PKG-INFO
docassemble.LAWVCommon.egg-info/SOURCES.txt
docassemble.LAWVCommon.egg-info/dependency_links.txt
docassemble.LAWVCommon.egg-info/not-zip-safe
docassemble.LAWVCommon.egg-info/top_level.txt
docassemble/LAWVCommon/__init__.py
docassemble/LAWVCommon/progressivedisclosure.py
docassemble/LAWVCommon/data/questions/common_info.yml
docassemble/LAWVCommon/data/sources/README.md
docassemble/LAWVCommon/data/static/README.md
docassemble/LAWVCommon/data/static/force_lightmode.js
docassemble/LAWVCommon/data/static/lawv.css
docassemble/LAWVCommon/data/static/progressivedisclosure.css
docassemble/LAWVCommon/data/templates/README.md
docassemble/LAWVCommon/data/templates/civil_case_info.pdf
docassemble/LAWVCommon/data/templates/dom_civil_case_info.pdf
docassemble/LAWVCommon/data/templates/dual_civil_case_info.pdf