Metadata-Version: 2.4
Name: docassemble.LAWVCommon
Version: 1.0.13
Summary: A docassemble extension for LAWV information used across multiple interviews
Home-page: https://docassemble.org
Author: System Administrator
Author-email: dhenry@lawv.net
License: The MIT License (MIT)
License-File: LICENSE
Dynamic: author
Dynamic: author-email
Dynamic: description
Dynamic: description-content-type
Dynamic: home-page
Dynamic: license
Dynamic: license-file
Dynamic: summary
